{
    "listings": [
        {
            "services" : ["Interior Design","Exterior Painting"],
            "name": "Contractor 1",
            "distance": "0.5",
            "rating": "4.5",
            "profileimage": "../assets/images/findpros/contractorpfp/1.jpeg",
            "images": [
                "../assets/images/findpros/contractorsplash/2.png",
                "../assets/images/findpros/icons/all.png"
            ]
        },
        {
            "services" : ["Interior Design"],
            "name": "Contractor 2",
            "distance": "30",
            "rating": "4.2",
            "profileimage": "../assets/images/findpros/contractorpfp/2.jpeg",
            "images": [
                "../assets/images/findpros/contractorsplash/1.jpeg",
                "../assets/images/findpros/icons/all.png"
            ]
        },
        {
            "services" : ["Interior Design","Exterior Painting","Interior Painting"],
            "name": "Contractor 3",
            "distance": "69",
            "rating": "3.5",
            "profileimage": "../assets/images/findpros/contractorpfp/2.jpeg",
            "images": [
                "../assets/images/findpros/contractorsplash/1.jpeg",
                "../assets/images/findpros/icons/all.png"
            ]
        }
    ]
}